CHANGELOG
LICENSE
MANIFEST.in
WAIVER
WAIVER.asc
requirements.txt
setup.cfg
setup.py
test_requirements.txt
chaind/dispatch.py
chaind/driver.py
chaind/error.py
chaind/filter.py
chaind/lock.py
chaind/session.py
chaind/settings.py
chaind/setup.py
chaind.egg-info/PKG-INFO
chaind.egg-info/SOURCES.txt
chaind.egg-info/dependency_links.txt
chaind.egg-info/requires.txt
chaind.egg-info/top_level.txt
chaind/adapters/base.py
chaind/adapters/fs.py
chaind/cli/arg.py
chaind/cli/base.py
chaind/cli/config.py
chaind/data/__init__.py
chaind/data/config/config.ini
chaind/data/config/token.ini
chaind/data/config/syncer/config.ini
chaind/unittest/common.py
chaind/unittest/fs.py
tests/test_fs.py