Metadata-Version: 2.1
Name: chaind
Version: 0.4.0
Summary: Base package for chain queue service
Home-page: https://git.defalsify.org/chaind
Author: Louis Holbrook
Author-email: dev@holbrook.no
License: AGPLv3+
Keywords: blockchain,cryptocurrency,dlt
Classifier: Programming Language :: Python :: 3
Classifier: Operating System :: OS Independent
Classifier: Development Status :: 3 - Alpha
Classifier: Environment :: Console
Classifier: Intended Audience :: Developers
Classifier: License :: OSI Approved :: GNU Affero General Public License v3 or later (AGPLv3+)
Classifier: Topic :: Internet
Requires-Python: >=3.8
Provides-Extra: postgres
Provides-Extra: sqlite
License-File: LICENSE
